sharktopoda_client/__init__.py
sharktopoda_client/client.py
sharktopoda_client/dto.py
sharktopoda_client/localization.py
sharktopoda_client/log.py
sharktopoda_client/udp.py
sharktopoda_client-0.4.5.dist-info/LICENSE
sharktopoda_client-0.4.5.dist-info/METADATA
sharktopoda_client-0.4.5.dist-info/WHEEL
sharktopoda_client-0.4.5.dist-info/RECORD
